scrapy_cookies/VERSION
scrapy_cookies/__init__.py
scrapy_cookies/downloadermiddlewares/__init__.py
scrapy_cookies/downloadermiddlewares/cookies.py
scrapy_cookies/settings/__init__.py
scrapy_cookies/settings/default_settings.py
scrapy_cookies/storage/__init__.py
scrapy_cookies/storage/in_memory.py
scrapy_cookies/storage/mongo.py
scrapy_cookies/storage/redis_.py
scrapy_cookies/storage/sqlite.py
scrapy_cookies_fixed-0.3.6.1.dist-info/METADATA
scrapy_cookies_fixed-0.3.6.1.dist-info/WHEEL
scrapy_cookies_fixed-0.3.6.1.dist-info/top_level.txt
scrapy_cookies_fixed-0.3.6.1.dist-info/RECORD
