Metadata-Version: 2.1
Name: scrapy-cookies-fixed
Version: 0.3.6.1
Summary: A fixed version of scrapy-cookie with updated imports
Author: aveaxii
Author-email: kimalex2004dev@gmail.com
Requires-Python: >=3.9
